{"history":{"2024-05-12":{"words":98,"characters":580,"sentences":16,"pages":0.20000000000000007,"files":126,"footnotes":0,"citations":0,"totalWords":88532,"totalCharacters":904835,"totalSentences":2898,"totalFootnotes":143,"totalCitations":143,"totalPages":177.00000000000003},"2024-05-13":{"words":0,"characters":0,"sentences":0,"pages":0,"files":0,"footnotes":0,"citations":0,"totalWords":88556,"totalCharacters":904963,"totalSentences":2898,"totalFootnotes":0,"totalCitations":0,"totalPages":177.00000000000003}},"modifiedFiles":{}}